audiotube/__init__.py
audiotube/download.py
audiotube/objects.py
audiotube/searching.py
audiotube/version.py
audiotube/youtube.py
audiotube-0.2.1.dist-info/LICENSE
audiotube-0.2.1.dist-info/METADATA
audiotube-0.2.1.dist-info/WHEEL
audiotube-0.2.1.dist-info/top_level.txt
audiotube-0.2.1.dist-info/RECORD
