Metadata-Version: 2.1
Name: audiotube
Version: 0.2.1
Summary: Easily can get audio and 'standard' captions from YouTube
Home-page: https://github.com/mzntaka0/audiotube
Author: Takao Mizuno
Author-email: takao.mizuno110@gmail.com
License: Apache Software License
Platform: UNKNOWN
Classifier: License :: OSI Approved :: Apache Software License
Classifier: Intended Audience :: Developers
Classifier: Programming Language :: Python :: 3.5
Classifier: Programming Language :: Python :: 3.6
Classifier: Operating System :: OS Independent
Classifier: Topic :: Software Development
Classifier: Topic :: Software Development :: Testing
Requires-Dist: tqdm
Requires-Dist: google-api-python-client
Requires-Dist: oauth2client
Requires-Dist: apiclient
Requires-Dist: youtube-dl
Requires-Dist: python-dotenv
Requires-Dist: beautifulsoup4
Requires-Dist: youtube-transcript-api
